cdk_quicksight_constructs/__init__.py
cdk_quicksight_constructs/py.typed
cdk_quicksight_constructs/_jsii/__init__.py
cdk_quicksight_constructs/_jsii/cdk-quicksight-constructs@0.1.5.jsii.tgz
cdk_quicksight_constructs-0.1.5.dist-info/LICENSE
cdk_quicksight_constructs-0.1.5.dist-info/METADATA
cdk_quicksight_constructs-0.1.5.dist-info/WHEEL
cdk_quicksight_constructs-0.1.5.dist-info/top_level.txt
cdk_quicksight_constructs-0.1.5.dist-info/RECORD
